jinja_to_excel/ExcelGenerator.py
jinja_to_excel/ExcelXMLMerger.py
jinja_to_excel/JinjaExcelEngine.py
jinja_to_excel/__init__.py
jinja_to_excel/cell_type/AreaChart.py
jinja_to_excel/cell_type/AreaChart3D.py
jinja_to_excel/cell_type/BarChart.py
jinja_to_excel/cell_type/BarChart3D.py
jinja_to_excel/cell_type/Chart.py
jinja_to_excel/cell_type/DateTime.py
jinja_to_excel/cell_type/General.py
jinja_to_excel/cell_type/Img.py
jinja_to_excel/cell_type/Number.py
jinja_to_excel/cell_type/PieChart.py
jinja_to_excel/cell_type/PieChart3D.py
jinja_to_excel/helper/DimensionHelper.py
jinja_to_excel/helper/GetAlignment.py
jinja_to_excel/helper/GetBorder.py
jinja_to_excel/helper/GetFill.py
jinja_to_excel/helper/GetFont.py
jinja_to_excel/helper/MergeCell.py
jinja_to_excel/helper/setCellStyle.py
jinja_to_excel/helper/setSheetAttr.py
jinja_to_excel/helper/setxmlattr.py
jinja_to_excel/helper/typeconverter.py
jinja_to_excel/helper/utils.py
jinja_to_excel-1.0.1.dist-info/LICENSE
jinja_to_excel-1.0.1.dist-info/METADATA
jinja_to_excel-1.0.1.dist-info/WHEEL
jinja_to_excel-1.0.1.dist-info/RECORD
